calcx/__init__.py
calcx/_version.py
calcx/calcx.py
calcx/perf_attrib.py
calcx/periods.py
calcx-0.0.3.dist-info/LICENSE
calcx-0.0.3.dist-info/METADATA
calcx-0.0.3.dist-info/WHEEL
calcx-0.0.3.dist-info/top_level.txt
calcx-0.0.3.dist-info/RECORD
